dtocean_reliability/__init__.py
dtocean_reliability-3.0.0.dist-info/METADATA
dtocean_reliability-3.0.0.dist-info/WHEEL
dtocean_reliability-3.0.0.dist-info/RECORD
